MANIFEST.in
README.md
VERSION
setup.py
talker/__init__.py
talker/client.py
talker/command.py
talker/config.py
talker/errors.py
talker/reactor.py
talker/utils.py
talker.egg-info/PKG-INFO
talker.egg-info/SOURCES.txt
talker.egg-info/dependency_links.txt
talker.egg-info/requires.txt
talker.egg-info/top_level.txt
talker_agent/__init__.py
talker_agent/talker.py