Metadata-Version: 2.1
Name: talker
Version: 1.9.7
Summary: The almighty remote command executor for Unix machines
Home-page: https://github.com/weka-io/talker
Author: Doron Cohen
Author-email: doron@weka.io
License: BSD
Platform: UNKNOWN
Classifier: Programming Language :: Python :: 3.4
Classifier: Programming Language :: Python :: 3.5
Classifier: Programming Language :: Python :: 3.6
Classifier: Programming Language :: Python :: 3.7
Classifier: Topic :: Communications
Classifier: Development Status :: 4 - Beta
Classifier: Intended Audience :: Developers
Classifier: Operating System :: Unix
Classifier: Operating System :: MacOS
Classifier: License :: OSI Approved :: BSD License
Provides-Extra: dev
Provides-Extra: test
